colorevo/__init__.py
colorevo/acq_cv2.py
colorevo/colors.py
colorevo/configuration.py
colorevo/h5writer.py
colorevo/maingui.py
colorevo/icons/document-new-from-template.svg
colorevo/icons/document-save-as-template.svg
colorevo/icons/draw-polyline.svg
colorevo/icons/draw-rectangle.svg
colorevo/icons/edit-clear-history.svg
colorevo/icons/list-add.svg
colorevo/icons/media-playback-stop.svg
colorevo/icons/media-record.svg
colorevo/icons/office-chart-line-stacked.svg
colorevo/icons/video-x-generic.svg
colorevo/icons/view-preview.svg
colorevo/icons/view-refresh.svg
colorevo-1.0.3.dist-info/LICENSE
colorevo-1.0.3.dist-info/METADATA
colorevo-1.0.3.dist-info/WHEEL
colorevo-1.0.3.dist-info/entry_points.txt
colorevo-1.0.3.dist-info/top_level.txt
colorevo-1.0.3.dist-info/RECORD
