Metadata-Version: 2.1
Name: colorevo
Version: 1.0.3
Summary: Analyze color evolution in ROIs of videos
Author-email: Carlos Pascual-Izarra <cpascual@users.sourceforge.net>
License: GNU GENERAL PUBLIC LICENSE
Project-URL: Homepage, https://gitlab.com/c-p/colorevo
Project-URL: Repository, https://gitlab.com/c-p/colorevo
Project-URL: Issues, https://gitlab.com/c-p/colorevo/issues
Keywords: colorevo
Classifier: Development Status :: 5 - Production/Stable
Classifier: Environment :: X11 Applications :: Qt
Classifier: Environment :: Win32 (MS Windows)
Classifier: Intended Audience :: Science/Research
Classifier: License :: OSI Approved :: GNU General Public License v3 or later (GPLv3+)
Classifier: Operating System :: Microsoft :: Windows
Classifier: Operating System :: POSIX
Classifier: Operating System :: POSIX :: Linux
Classifier: Operating System :: Unix
Classifier: Operating System :: OS Independent
Classifier: Programming Language :: Python :: 3
Classifier: Topic :: Scientific/Engineering
Requires-Python: >=3.12
License-File: LICENSE
Requires-Dist: click >=8.1.7
Requires-Dist: h5py >=3.12.1
Requires-Dist: numpy >=2.1.1
Requires-Dist: opencv-python-headless >=4.10.0.84
Requires-Dist: pyqt6 >=6.7.1
Requires-Dist: pyqtgraph >=0.13.7
Provides-Extra: test
Requires-Dist: pytest >=8.3.3 ; extra == 'test'
